README
setup.py
./__init__.py
./health_ophthalmology.py
./health_ophthalmology_report.xml
./health_ophthalmology_view.xml
./tryton.cfg
./icons/ophthalmology.svg
./locale/ar.po
./locale/de.po
./locale/el.po
./locale/es.po
./locale/fr.po
./locale/it_IT.po
./locale/ja_JP.po
./locale/lo.po
./locale/pt_BR.po
./locale/zh_CN.po
./report/ophthalmology.odt
./tests/__init__.py
./tests/test_health_ophthalmology.py
./view/findings_form.xml
./view/findings_tree.xml
./view/oph_form.xml
./view/oph_tree.xml
trytond_health_ophthalmology.egg-info/PKG-INFO
trytond_health_ophthalmology.egg-info/SOURCES.txt
trytond_health_ophthalmology.egg-info/dependency_links.txt
trytond_health_ophthalmology.egg-info/entry_points.txt
trytond_health_ophthalmology.egg-info/not-zip-safe
trytond_health_ophthalmology.egg-info/requires.txt
trytond_health_ophthalmology.egg-info/top_level.txt